distiller/__init__.py
distiller/base.py
distiller/helpers.py
distiller/nodes.py
distiller/json/__init__.py
distiller/markup/__init__.py
distiller/markup/mapper.py
distiller/markup/parser.py
distiller/markup/preprocessor.py
pydantic_distiller-0.2.5.dist-info/LICENSE
pydantic_distiller-0.2.5.dist-info/WHEEL
pydantic_distiller-0.2.5.dist-info/METADATA
pydantic_distiller-0.2.5.dist-info/RECORD
